factfinder/__init__.py
factfinder/aggregated_geography.py
factfinder/data/acs/2018/median.json
factfinder/data/acs/2018/metadata.json
factfinder/data/acs/2018/special.json
factfinder/data/acs/2019/median.json
factfinder/data/acs/2019/metadata.json
factfinder/data/acs/2019/special.json
factfinder/data/decennial/2010/median.json
factfinder/data/decennial/2010/metadata.json
factfinder/data/decennial/2010/special.json
factfinder/data/lookup_geo/2010/lookup_geo.csv
factfinder/main.py
factfinder/median.py
factfinder/special.py
factfinder/utils.py
factfinder/variable.py
pff_factfinder-0.0.6.dist-info/LICENSE
pff_factfinder-0.0.6.dist-info/WHEEL
pff_factfinder-0.0.6.dist-info/METADATA
pff_factfinder-0.0.6.dist-info/RECORD
