Metadata-Version: 2.1
Name: pff-factfinder
Version: 0.0.6
Summary: 
Author: Baiyue Cao
Author-email: caobaiyue@live.com
Requires-Python: >=3.6.1,<4.0.0
Classifier: Programming Language :: Python :: 3
Classifier: Programming Language :: Python :: 3.7
Classifier: Programming Language :: Python :: 3.8
Classifier: Programming Language :: Python :: 3.9
Requires-Dist: cached-property (==1.5.2)
Requires-Dist: census (==0.8.15)
Requires-Dist: pandas (==1.1.4)
Requires-Dist: python-dotenv (==0.15.0)
Requires-Dist: tqdm (>=4.56.0,<5.0.0)
Requires-Dist: typer (==0.3.2)
